{
  "_fv": 60,
  "_type": "recipe",
  "definition": {
    "recipeType": "Smithing",
    "recipeRetstackSize": 1,
    "group": "elementium_mod",
    "cookingBookCategory": "MISC",
    "xpReward": 0.0,
    "cookingTime": 200,
    "craftingBookCategory": "MISC",
    "recipeShapeless": false,
    "smithingInputStack": {
      "value": "CUSTOM:ElementiumShovel"
    },
    "smithingInputAdditionStack": {
      "value": "CUSTOM:FireEssence"
    },
    "smithingReturnStack": {
      "value": "CUSTOM:ElementfireShovel"
    },
    "name": "elementfire_shovel_recipe",
    "namespace": "mod"
  }
}