{
  "_fv": 60,
  "_type": "tool",
  "definition": {
    "toolType": "Axe",
    "renderType": 0,
    "blockingRenderType": 0,
    "texture": "elementnatureaxe",
    "customModelName": "Normal",
    "blockingModelName": "Normal blocking",
    "name": "Elementium Axe (Element:nature)",
    "specialInformation": {
      "fixedValue": [
        "Chops  down  the whole tree..  w.i.p."
      ]
    },
    "creativeTab": {
      "value": "CUSTOM:ElementiumTab"
    },
    "harvestLevel": 6,
    "efficiency": 15.0,
    "attackSpeed": 5.5,
    "enchantability": 22,
    "damageVsEntity": 9.0,
    "usageCount": 1212,
    "blocksAffected": [],
    "repairItems": [
      {
        "value": "CUSTOM:NatureEssence"
      }
    ],
    "immuneToFire": false,
    "stayInGridWhenCrafting": false,
    "damageOnCrafting": false,
    "onRightClickedOnBlock": {
      "name": "ElementnatureAxeRightclickedOnBlock"
    }
  }
}